sharanga/__init__.py
sharanga/scanner.py
sharanga-1.0.dist-info/licenses/LICENSE
sharanga-1.0.dist-info/METADATA
sharanga-1.0.dist-info/WHEEL
sharanga-1.0.dist-info/entry_points.txt
sharanga-1.0.dist-info/top_level.txt
sharanga-1.0.dist-info/RECORD
