Metadata-Version: 2.4
Name: sharanga
Version: 1.0
Summary: Sharanga is a fast, asynchronous port scanner written in Python. It supports domain/IP/CIDR scanning, custom ports, banner grabbing, and service detection. Ideal for recon, pentesting, and network analysis.
Home-page: https://github.com/R0X4R/sharanga
Author: Eshan Singh
Author-email: r0x4r@yahoo.com
License: MIT
Classifier: Environment :: Console
Classifier: Intended Audience :: Developers
Classifier: Intended Audience :: Information Technology
Classifier: Intended Audience :: System Administrators
Classifier: Operating System :: OS Independent
Classifier: Programming Language :: Python
Classifier: Programming Language :: Python :: 3
Classifier: Topic :: Security
Classifier: Topic :: Internet
Classifier: Topic :: Software Development :: Libraries :: Python Modules
Classifier: Topic :: System :: Networking :: Monitoring
Classifier: Topic :: Utilities
Requires-Python: >=3.7
License-File: LICENSE
Dynamic: author
Dynamic: author-email
Dynamic: classifier
Dynamic: description
Dynamic: description-content-type
Dynamic: home-page
Dynamic: license
Dynamic: license-file
Dynamic: requires-python
Dynamic: summary
